{
  "parent": "statues:husk_statue",
  "criteria": {
    "spider_statue": {
      "conditions": {
        "items": [
          {
            "items": [
              "statues:spider_statue"
            ]
          }
        ]
      },
      "trigger": "minecraft:inventory_changed"
    }
  },
  "display": {
    "description": {
      "translate": "advancement.statues.spider_statue.desc"
    },
    "icon": {
      "item": "statues:spider_statue"
    },
    "title": {
      "translate": "advancement.statues.spider_statue.title"
    }
  },
  "requirements": [
    [
      "spider_statue"
    ]
  ],
  "sends_telemetry_event": true
}